realerikrani/baseclient/__init__.py
realerikrani/baseclient/adapter.py
realerikrani/baseclient/client.py
realerikrani/baseclient/py.typed
realerikrani_baseclient-1.0.1.dist-info/LICENSE
realerikrani_baseclient-1.0.1.dist-info/METADATA
realerikrani_baseclient-1.0.1.dist-info/NOTICE
realerikrani_baseclient-1.0.1.dist-info/WHEEL
realerikrani_baseclient-1.0.1.dist-info/top_level.txt
realerikrani_baseclient-1.0.1.dist-info/RECORD
