Metadata-Version: 2.2
Name: realerikrani-baseclient
Version: 1.0.1
Summary: Foundation for building API clients. A wrapper around requests.
License: Apache-2.0
Project-URL: Repository, https://github.com/realerikrani/baseclient
Requires-Python: >=3.11
License-File: LICENSE
License-File: NOTICE
Requires-Dist: requests==2.*
